{
  "name": "pgauthz",
  "abstract": "Zanzibar-style authorization as a Postgres extension",
  "description": "pgauthz brings Google Zanzibar-style relationship-based authorization directly into PostgreSQL. Define authorization policies, write relationship tuples, and check permissions \u2014 all from SQL.",
  "version": "0.2.2",
  "maintainer": [
    "pgauthz contributors"
  ],
  "license": "mit",
  "prereqs": {
    "runtime": {
      "requires": {
        "PostgreSQL": "16.0.0"
      }
    }
  },
  "provides": {
    "pgauthz": {
      "abstract": "Zanzibar-style authorization functions for PostgreSQL",
      "file": "crates/pgauthz/pgauthz.control",
      "version": "0.2.2"
    }
  },
  "resources": {
    "homepage": "https://github.com/zvectorlabs/pgauthz",
    "bugtracker": {
      "web": "https://github.com/zvectorlabs/pgauthz/issues"
    },
    "repository": {
      "url": "https://github.com/zvectorlabs/pgauthz.git",
      "web": "https://github.com/zvectorlabs/pgauthz",
      "type": "git"
    }
  },
  "generated_by": "hand",
  "meta-spec": {
    "version": "1.0.0",
    "url": "https://pgxn.org/spec/"
  }
}
